pyiaso/__init__.py
pyiaso/main.py
pyiaso/monitor.py
pyiaso/utils.py
pyiaso/actions/__init__.py
pyiaso/actions/helpers/__init__.py
pyiaso/actions/helpers/command.py
pyiaso/actions/helpers/docker.py
pyiaso/checks/__init__.py
pyiaso/checks/default.py
pyiaso/checks/docker.py
pyiaso/checks/http.py
pyiaso/notifications/__init__.py
pyiaso/notifications/helpers/__init__.py
pyiaso/notifications/helpers/console.py
pyiaso/notifications/helpers/sendgrid.py
py_iaso-0.2.0.dist-info/LICENSE
py_iaso-0.2.0.dist-info/METADATA
py_iaso-0.2.0.dist-info/WHEEL
py_iaso-0.2.0.dist-info/entry_points.txt
py_iaso-0.2.0.dist-info/top_level.txt
py_iaso-0.2.0.dist-info/RECORD
