Metadata-Version: 2.1
Name: py-iaso
Version: 0.2.0
Summary: UNKNOWN
Home-page: UNKNOWN
Author: UNKNOWN
Author-email: UNKNOWN
License: UNKNOWN
Platform: UNKNOWN
Requires-Dist: pyyaml
Requires-Dist: requests
Requires-Dist: docker
Requires-Dist: sendgrid
